traderepo/__init__.py
traderepo/repository/TradeRepository.py
traderepo/repository/__init__.py
traderepo/repository/serialize/__init__.py
traderepo/repository/serialize/trade_deserializer.py
traderepo/repository/serialize/trade_serializer.py
persuader_technology_automata_trade_repository-0.1.7.dist-info/LICENSE
persuader_technology_automata_trade_repository-0.1.7.dist-info/METADATA
persuader_technology_automata_trade_repository-0.1.7.dist-info/WHEEL
persuader_technology_automata_trade_repository-0.1.7.dist-info/top_level.txt
persuader_technology_automata_trade_repository-0.1.7.dist-info/RECORD
