Metadata-Version: 2.1
Name: persuader-technology-automata-trade-repository
Version: 0.1.7
Summary: Automata Trade Repository
Author: Persuader Technology
Author-email: software@persuader.technology
License: UNLICENSE
Classifier: Programming Language :: Python :: 3
License-File: LICENSE
Requires-Dist: persuader-technology-automata-core (>=0.6.0)
Requires-Dist: persuader-technology-automata-redis (>=0.3.8)
